geojson_aoi/__init__.py
geojson_aoi/__version__.py
geojson_aoi/dbconfig.py
geojson_aoi/normalize.py
geojson_aoi/types.py
geojson_aoi/_async/__init__.py
geojson_aoi/_async/parser.py
geojson_aoi/_async/postgis.py
geojson_aoi/_sync/__init__.py
geojson_aoi/_sync/parser.py
geojson_aoi/_sync/postgis.py
geojson_aoi_parser-0.3.5.dist-info/METADATA
geojson_aoi_parser-0.3.5.dist-info/WHEEL
geojson_aoi_parser-0.3.5.dist-info/licenses/LICENSE.md
geojson_aoi_parser-0.3.5.dist-info/RECORD
