Metadata-Version: 2.4
Name: geojson-aoi-parser
Version: 0.3.5
Summary: Parse and normalize a GeoJSON area of interest, using PostGIS.
Author-email: Sam Woodcock <sam.woodcock@hotosm.org>, Luke Everhart <luke.f.everhart@gmail.com>
License: GPL-3.0-only
License-File: LICENSE.md
Keywords: aoi,geojson,hotosm,normalize,parser
Classifier: Programming Language :: Python :: 3
Classifier: Programming Language :: Python :: 3.10
Classifier: Programming Language :: Python :: 3.11
Classifier: Programming Language :: Python :: 3.12
Classifier: Topic :: Scientific/Engineering :: GIS
Classifier: Topic :: Utilities
Requires-Python: >=3.10
Requires-Dist: psycopg>=3.1
